{
    "parent": "lotr:rohan/common",
    "speech": [{
            "conditions": {
                "relation": "friendly"
            },
            "lines": [
                "我们是马克的农夫和驭马人。",
                "就是白手的奥克敢来，我也要和他们干一架！",
                "我真想同国王并肩作战！",
                "奥克正在山里繁殖，我真替家人们担心，#p。",
                "我很担心我们这些百姓。",
                "据说有黑地的爪牙三更半夜来偷我们的马儿，我想想都害怕，#p。",
                "有人说太阳河南边儿的暴徒正聚集起来准备攻打石国。",
                "马儿呢？骑手呢？远远不够，我们需要更多！"
            ]
        },
        {
            "conditions": {
                "relation": "friendly",
                "rank": "<=guest",
                "biome": "#home"
            },
            "lines": [
                "什么风把你送来了？",
                "你可不是什么巫师的眼线吧，#p？",
                "白袍巫师手下有很多眼线，你不是吧？"
            ]
        },
        {
            "conditions": {
                "relation": "friendly",
                "rank": ">=atarms"
            },
            "lines": [
                "有人说国王病了，和以前大相径庭。",
                "国王该来的时候怎么不来？他的骑手呢，#p？",
                "大家庄稼无收，马匹被偷，国王病情日渐愈下。"
            ]
        },
        {
            "conditions": {
                "relation": "hostile"
            },
            "lines": [
                "你这恶棍！",
                "别让我看见你，#p！",
                "你这鼠辈，是想干什么？",
                "你这恶棍！滚回老家去吧！",
                "你比野人还招人嫌！",
                "别碰我的马儿！",
                "快滚！你这恶徒！",
                "像你这样的懒屁股别来招惹我！",
                "你是什么东西，#p？土匪、半兽人、还是艾森加德的走狗？",
                "离我远点！",
                "我和你没啥好说的！"
            ]
        },
        {
            "conditions": {
                "relation": "hostile",
                "biome": "#home"
            },
            "lines": [
                "你最好赶紧离开，#p。",
                "快出去吧，不然国王的骑手会赶走你！",
                "这里不是你这种家伙该来的地方。",
                "洛汗英雄会把你打得半死不活，#p！",
                "国王的骑手会把你揍个七荤八素，#p！",
                "守卫！快来！",
                "滚出去，#p！这里不允许邪恶踏足！",
                "你这样的恶棍不该出现在这儿！",
                "洛汗不欢迎你和你的家伙什！",
                "带着你和你的东西离开马克！",
                "这里不欢迎你这种鼠辈！"
            ]
        },
        {
            "conditions": {
                "relation": "hostile",
                "pledge": "lotr:isengard"
            },
            "lines": [
                "你这东西，竟给白手效命！",
                "滚啊！艾森加德的爪牙！",
                "你这听命白袍巫师的鬼东西！快滚！"
            ]
        },
        {
            "conditions": {
                "relation": "hostile",
                "pledge": "lotr:dunland"
            },
            "lines": [
                "滚吧！黑蛮地的东西！",
                "快滚！黑蛮地的爪牙！"
            ]
        },
        {
            "conditions": {
                "relation": "hostile",
                "pledge": "lotr:mordor | lotr:near_harad | lotr:rhudel"
            },
            "lines": [
                "你这听命于黑暗魔君的东西！",
                "快滚！魔多的爪牙！"
            ]
        },
        {
            "conditions": {
                "relation": "hostile",
                "pledge_relation": "bad"
            },
            "lines": [
                "你这投奔大敌的东西！",
                "快滚！大敌的爪牙！"
            ]
        }
    ]
}